[
  {
    "title": "Sun #1002",
    "author": "tori28",
    "volume": 4.4,
    "Floor": 0.4
  },
  {
    "title": "Sun #1002",
    "author": "tori28",
    "volume": 4.4,
    "Floor": 0.4
  },
  {
    "title": "Sun #1002",
    "author": "tori28",
    "volume": 4.4,
    "Floor": 0.4
  },
  {
    "title": "Sun #1002",
    "author": "tori28",
    "volume": 4.4,
    "Floor": 0.4
  },
  {
    "title": "Sun #1002",
    "author": "tori28",
    "volume": 4.4,
    "Floor": 0.4
  },
  {
    "title": "Sun #1002",
    "author": "tori28",
    "volume": 4.4,
    "Floor": 0.4
  },
  {
    "title": "Sun #1002",
    "author": "tori28",
    "volume": 4.4,
    "Floor": 0.4
  },
  {
    "title": "Sun #1002",
    "author": "tori28",
    "volume": 4.4,
    "Floor": 0.4
  }
]
